nex/__init__.py
nex/main.py
worldnex-2.0.1.dist-info/licenses/LICENSE
worldnex-2.0.1.dist-info/METADATA
worldnex-2.0.1.dist-info/WHEEL
worldnex-2.0.1.dist-info/top_level.txt
worldnex-2.0.1.dist-info/RECORD
