Metadata-Version: 2.4
Name: worldnex
Version: 2.0.1
Summary: Helps you remotely access your Computer
Author-email: world <kasramoradi517@gmail.com>
Project-URL: Homepage, https://github.com/world0011/Nex
License-File: LICENSE
Requires-Dist: discord.py==1.7.3
Requires-Dist: pyautogui
Requires-Dist: requests
Requires-Dist: pywin32
Requires-Dist: pycryptodomex
Requires-Dist: keyboard
Requires-Dist: pyperclip
Requires-Dist: opencv-python
Requires-Dist: numpy
Requires-Dist: mss
Requires-Dist: screeninfo
Requires-Dist: pillow
Requires-Dist: pyvolume
Requires-Dist: pyinstaller
Dynamic: license-file
